{"thread_IW2328tKZ1IvBVBqNeQRKFx3": "15:12 - 24/9/2024", "thread_7FKhQNqB8RE6UQj7HEx5INu7": "15:41 - 24/9/2024", "thread_WnvBaeZV7XEdv7hWwK4Mc3En": "16:14 - 24/9/2024", "thread_NVGXeFWcP4XwRVx7m14YJ9mm": "16:23 - 24/9/2024", "thread_DBMJtf95HWYlxFjxD5tPeWRk": "17:7 - 24/9/2024", "thread_z8KM1ojco2oOK50dDzFC7Q5w": "10:25 - 25/9/2024", "thread_pc4To1MF1FNqwkvramaJtSii": "11:9 - 25/9/2024", "thread_NrOuolmLzL3KloC6T5I5vINJ": "12:23 - 25/9/2024", "thread_gLsmr8vpdZUNQEi4p3GYRKXA": "13:4 - 25/9/2024", "thread_bysQW4Ki0fA3e0Qj9fIUWSpM": "13:8 - 25/9/2024", "thread_pFk1DnsqnHus62eeUa9DoJrx": "13:10 - 25/9/2024", "thread_AdxV59Czv641fAFhiMN6yiWz": "13:18 - 25/9/2024", "thread_vPpeUNJYQbFHn0goK0fKK2kG": "15:18 - 25/9/2024", "thread_x3etKtBTBsN0U52kZ3G0Vvoi": "15:33 - 25/9/2024", "thread_Lim0HEfZFGITkk0URGWCK9T3": "15:35 - 25/9/2024", "thread_Xr7OWmchDUNd2UqiV4cZS4T4": "15:37 - 25/9/2024", "thread_cO4rtR3biS4b3AmyCpxopuXe": "15:37 - 25/9/2024", "thread_XgYYWgEdwTJ14I5tk4lpz6BJ": "15:43 - 25/9/2024", "thread_pfsX7hoQIUtXz1sFtNFUEqBU": "15:46 - 25/9/2024", "thread_PyWNFuKU8OeFrL3wcSp0Fk4b": "15:51 - 25/9/2024", "thread_GIADIQgcqaC4NhVkqfurWhKW": "9:26 - 26/9/2024", "thread_S7GcNGrGy3np6FAK5MatXmbF": "9:29 - 26/9/2024", "thread_mjHopTyubLH6L6rqbzKc0WD0": "9:42 - 26/9/2024", "thread_XYhsGAa38Ig6v8zj47br7TC0": "10:27 - 26/9/2024", "thread_15wu2T4QjgmkR8PE9yCKdPzW": "13:50 - 26/9/2024", "thread_0OaldrH7iMLf2WD8dOt8nDAD": "14:58 - 26/9/2024", "thread_YIU1WI6bgQA3iSPKbukCWSww": "15:15 - 26/9/2024", "thread_82JBjGDFPWrPfp3FaZ9Mbx41": "15:25 - 26/9/2024", "thread_vsf40O7xsYc43xxP3Xk1OyWC": "15:28 - 26/9/2024", "thread_lc9Sa8kNzEXPOaPewL5hTK9f": "15:35 - 26/9/2024", "thread_JqHS11pnaEpFVQgy2YCRBDol": "15:36 - 26/9/2024", "thread_jeXX7gAYqyGTinuKTMZCVFx5": "15:41 - 26/9/2024", "thread_aylF7LVwV6gqlC13ECOzKvpX": "15:48 - 26/9/2024", "thread_4FMHyOKiC8DQqiuxneX8gVZd": "15:49 - 26/9/2024", "thread_efPNEqQXcohaj1Pyp0M2Cmc2": "16:10 - 26/9/2024", "thread_8T1GIkzM4YzfjjIk2yKr95dh": "16:11 - 26/9/2024", "thread_EGtbjtMPA8R2IiiGQVHM4kSV": "16:16 - 26/9/2024", "thread_qIT9UbZx7emsc4tz6YgGInSQ": "16:33 - 26/9/2024", "thread_hPfizlYEKGpnC1ru8DsOituC": "16:40 - 26/9/2024", "thread_R2oYXW7c78tRK8tVMZ6khJzT": "16:46 - 26/9/2024", "thread_z6PmnAKjgfCEejSk5gioplmx": "16:52 - 26/9/2024", "thread_NsBghEAbRvatQPbQuBSiHtwB": "16:53 - 26/9/2024", "thread_OSNOt3ywFOsPdv9b8mnhNmeJ": "16:56 - 26/9/2024", "thread_YsQERBHHCWuWGNe2MzEbFVXf": "17:0 - 26/9/2024", "thread_itybYThKo1opMiBqLGy1qv5Y": "17:8 - 26/9/2024", "thread_sTxo9WA8f3xMen2j2T6DznsP": "17:12 - 26/9/2024", "thread_oOPAfbZEZIOFm077qhB8Hw5E": "17:17 - 26/9/2024", "thread_VjbpXVzTzSxGgSkgaEM9MAdx": "17:21 - 26/9/2024", "thread_sHFjPZ4YodbSPhS6HUwabZFk": "17:27 - 26/9/2024", "thread_EsChzPaJ2xMyQuhMB5FZCmyj": "17:29 - 26/9/2024", "thread_7JzX4S35uDgXbtii3htvweHb": "17:36 - 26/9/2024", "thread_MPoYhBkYLDLVN4WkyFzu70Km": "17:59 - 26/9/2024", "thread_Q66ErB6rVAfRua48tDuVAXZ6": "18:2 - 26/9/2024", "thread_w4CEBw1BfUYWdouJUx5VTK8H": "18:7 - 26/9/2024", "thread_S9mYz9JdV3qgSJin1N52qBKa": "18:12 - 26/9/2024", "thread_A1waCkT8eMHP55BdRhR3O3QM": "18:14 - 26/9/2024", "thread_rDRS6X1YQ0SrTTdRxlZmbNsu": "18:53 - 26/9/2024", "thread_olH0d6nMI8Hi4UTjwoGHQceg": "18:56 - 26/9/2024", "thread_BQFku3mhxBLD4gynGSf22BxW": "9:14 - 27/9/2024", "thread_7eIEE2PiWtP0RfaSrUIMLxzr": "9:16 - 27/9/2024", "thread_Is5GwkcKNSsiX55SOMGUC6gn": "9:17 - 27/9/2024", "thread_OXDPtW3PAxFZcYUfSFLNXhpj": "9:20 - 27/9/2024", "thread_WnmZNTebrBVL1vtFicqt0wof": "9:21 - 27/9/2024", "thread_XCU8dvQEYylTPfiNadF4QewR": "9:25 - 27/9/2024", "thread_bVT8jdnrieTxKeIPONnKH5y1": "10:4 - 27/9/2024", "thread_7Zvd3RYfELgaStuollUqWuYO": "10:7 - 27/9/2024", "thread_w9l5PVbLEzo8pMds5nSpnixZ": "10:26 - 27/9/2024", "thread_faeOTYPTJ3rCG3LA9PHAac4c": "10:29 - 27/9/2024", "thread_8EmjYNC6HbziVo7G6Sc0KTpP": "10:31 - 27/9/2024", "thread_Lg2DDX0g4cSVvOe8sOc40jC7": "10:36 - 27/9/2024", "thread_zdM43ekNG3h3I6J7rjm7dhoJ": "10:38 - 27/9/2024", "thread_vdDtRc1S9l9hIZBqpFkylBdZ": "10:40 - 27/9/2024", "thread_y9GxNszUDvlGsWjBbgdNT6IH": "10:44 - 27/9/2024", "thread_T3q0dYzY8OCVlrTKekeLhVEJ": "10:56 - 27/9/2024", "thread_CqrkhYqIhYIwhIKkWayBP30c": "13:13 - 27/9/2024", "thread_NZMYDR0pqG6Dz5ALrMFCHap6": "13:19 - 27/9/2024", "thread_GlX8VvW1steY5q1DuXObJOK2": "13:32 - 27/9/2024", "thread_D22VI9ESSLPEe0uVLoWOtpp8": "13:50 - 27/9/2024", "thread_TMp9Sw1zeHsFUAg5zj1JwEko": "13:53 - 27/9/2024", "thread_q0tLWvBuV2c3b2HoeWFyvqAB": "13:54 - 27/9/2024", "thread_4ORL5VSZmRphj9qsXZrvYolQ": "14:0 - 27/9/2024", "thread_mYFwNM3D4YextxipycEA9Z8C": "14:28 - 27/9/2024", "thread_jsdqKRpQQgNNsuainfcQeBM8": "14:38 - 27/9/2024"}